google_trendy/__init__.py
google_trendy/google_trendy.py
google_trendy-2.0.dist-info/licenses/LICENSE
google_trendy-2.0.dist-info/METADATA
google_trendy-2.0.dist-info/WHEEL
google_trendy-2.0.dist-info/top_level.txt
google_trendy-2.0.dist-info/RECORD
