Metadata-Version: 2.4
Name: google_trendy
Version: 2.0
Summary: Package for getting and analyzing tending Google searches
Home-page: https://github.com/michaelMondoro/google_trendy
Author: Michael Mondoro
Author-email: michaelmondoro@gmail.com
Classifier: Programming Language :: Python :: 3
Classifier: License :: OSI Approved :: MIT License
Classifier: Operating System :: OS Independent
Requires-Python: >=3.7
License-File: LICENSE
Requires-Dist: bs4
Requires-Dist: requests
Requires-Dist: lxml
Dynamic: author
Dynamic: author-email
Dynamic: classifier
Dynamic: description
Dynamic: description-content-type
Dynamic: home-page
Dynamic: license-file
Dynamic: requires-dist
Dynamic: requires-python
Dynamic: summary
